vector_bench/args.py
vector_bench/bench.py
vector_bench/log.py
vector_bench/main.py
vector_bench/spec.py
vector_bench/client/__init__.py
vector_bench/client/base.py
vector_bench/client/pgvecto_rs.py
vector_bench/client/pgvector.py
vector_bench/dataset/__init__.py
vector_bench/dataset/base.py
vector_bench/dataset/hdf5.py
vector_bench/dataset/pseudo.py
vector_bench/dataset/source.py
vector_bench-0.1.0.dist-info/METADATA
vector_bench-0.1.0.dist-info/WHEEL
vector_bench-0.1.0.dist-info/entry_points.txt
vector_bench-0.1.0.dist-info/top_level.txt
vector_bench-0.1.0.dist-info/RECORD
