Metadata-Version: 2.1
Name: vector-bench
Version: 0.1.0
Summary: Benchmark vector database/extensions.
Author-email: TensorChord <envd-maintainers@tensorchord.ai>
License: Apache-2.0
Project-URL: Homepage, https://github.com/tensorchord/vectordb-benchmark
Classifier: Intended Audience :: Developers
Requires-Python: >=3.8
Requires-Dist: msgspec ~=0.18.5
Requires-Dist: h5py ~=3.10.0
Requires-Dist: numpy ~=1.26.3
Requires-Dist: tqdm ~=4.66
Requires-Dist: httpx ~=0.25
Requires-Dist: psycopg[binary] ~=3.1
Provides-Extra: dev
Requires-Dist: ruff ~=0.1.3 ; extra == 'dev'
